wtot/__init__.py
wtot/version.py
wtot/wtot.py
wtot-1.0.0.dist-info/METADATA
wtot-1.0.0.dist-info/WHEEL
wtot-1.0.0.dist-info/entry_points.txt
wtot-1.0.0.dist-info/top_level.txt
wtot-1.0.0.dist-info/RECORD
