Metadata-Version: 2.1
Name: wtot
Version: 1.0.0
Summary: WordTranslationOnTerminal
Home-page: https://pypi.org/project/wtot/
Author: YeeKear
Author-email: 554408064@sjtu.edu.cn
License: UNKNOWN
Keywords: python dictionary terminal
Platform: UNKNOWN
Classifier: Environment :: Console
Classifier: Intended Audience :: Developers
Classifier: License :: OSI Approved :: MIT License
Classifier: Operating System :: OS Independent
Classifier: Programming Language :: Python
Classifier: Topic :: Terminals
Requires-Dist: termcolor
